procgenlib/__init__.py
procgenlib/synthesis/__init__.py
procgenlib/synthesis/_diamond_square.py
procgenlib-0.0.1.dist-info/LICENSE
procgenlib-0.0.1.dist-info/METADATA
procgenlib-0.0.1.dist-info/WHEEL
procgenlib-0.0.1.dist-info/top_level.txt
procgenlib-0.0.1.dist-info/RECORD
